demal/__init__.py
demal/demal.py
demal-2.1.0.dist-info/LICENSE.txt
demal-2.1.0.dist-info/METADATA
demal-2.1.0.dist-info/WHEEL
demal-2.1.0.dist-info/entry_points.txt
demal-2.1.0.dist-info/top_level.txt
demal-2.1.0.dist-info/RECORD
