Metadata-Version: 2.1
Name: demal
Version: 2.1.0
Summary: MAL (Meta Attack Language) to JSON decoding library and command-line tool.
Home-page: https://github.com/victorazzam/demal
Download-URL: https://github.com/victorazzam/demal/releases
Author: Victor Azzam
License: MIT
Classifier: Development Status :: 5 - Production/Stable
Classifier: Intended Audience :: Information Technology
Classifier: Intended Audience :: Developers
Classifier: License :: OSI Approved :: MIT License
Classifier: Operating System :: Microsoft :: Windows
Classifier: Operating System :: POSIX :: Linux
Classifier: Operating System :: MacOS
Classifier: Programming Language :: Python :: 3.8
Classifier: Programming Language :: Python :: 3.9
Classifier: Programming Language :: Python :: 3.10
Classifier: Programming Language :: Python :: 3.11
Requires-Python: >=3.8
License-File: LICENSE.txt
